ib_data_sdk/__init__.py
ib_data_sdk/cli.py
ib_data_sdk/client.py
ib_data_sdk/contracts.py
ib_data_sdk/enums.py
ib_data_sdk/exceptions.py
ib_data_sdk/models.py
ib_data_sdk/processors.py
ib_data_sdk-0.1.8.dist-info/licenses/LICENSE
ib_data_sdk-0.1.8.dist-info/METADATA
ib_data_sdk-0.1.8.dist-info/WHEEL
ib_data_sdk-0.1.8.dist-info/entry_points.txt
ib_data_sdk-0.1.8.dist-info/top_level.txt
ib_data_sdk-0.1.8.dist-info/RECORD
