Metadata-Version: 2.4
Name: ib-data-sdk
Version: 0.1.8
Summary: Interactive Brokers Data SDK
Author-email: Lim Yuan Sheng <yuansheng0424@gmail.com>
License: MIT
Project-URL: Homepage, https://github.com/quantphantom/ib-data-sdk
Project-URL: Documentation, https://github.com/quantphantom/ib-data-sdk/tree/main/docs
Project-URL: Source, https://github.com/quantphantom/ib-data-sdk
Requires-Python: >=3.8
License-File: LICENSE
Requires-Dist: ibapi>=9.81.1
Requires-Dist: pandas>=1.5.0
Requires-Dist: numpy>=1.23.0
Requires-Dist: requests>=2.28.0
Requires-Dist: rich>=13.8.0
Requires-Dist: typer==0.12.3
Requires-Dist: click==8.1.7
Dynamic: license-file
